dash_molstar/MolstarViewer.py
dash_molstar/__init__.py
dash_molstar/_imports_.py
dash_molstar/dash_molstar.min.js
dash_molstar/dash_molstar.min.js.map
dash_molstar/metadata.json
dash_molstar/package-info.json
dash_molstar/rcsb-molstar.js
dash_molstar/utils/__init__.py
dash_molstar/utils/molstar_helper.py
dash_molstar/utils/representation_params.json
dash_molstar/utils/representations.py
dash_molstar/utils/target.py
dash_molstar-1.3.1.dist-info/LICENSE
dash_molstar-1.3.1.dist-info/METADATA
dash_molstar-1.3.1.dist-info/WHEEL
dash_molstar-1.3.1.dist-info/top_level.txt
dash_molstar-1.3.1.dist-info/RECORD
