Metadata-Version: 2.1
Name: dash_molstar
Version: 1.3.1
Summary: The molstar plugin for plotly dash framework
Author: SimonSun <simonhrsun@gmail.com>
License: LGPL-2.1
Classifier: Framework :: Dash
License-File: LICENSE
